pyp.py
pypyp-1.2.0.dist-info/entry_points.txt
pypyp-1.2.0.dist-info/LICENSE
pypyp-1.2.0.dist-info/WHEEL
pypyp-1.2.0.dist-info/METADATA
pypyp-1.2.0.dist-info/RECORD
