Metadata-Version: 2.1
Name: pypyp
Version: 1.2.0
Summary: Easily run Python at the shell! Magical, but never mysterious.
Author: Shantanu Jain
Author-email: hauntsaninja@gmail.com
Requires-Python: >=3.8
Classifier: Environment :: Console
Classifier: Intended Audience :: Developers
Classifier: License :: OSI Approved :: MIT License
Classifier: Operating System :: OS Independent
Classifier: Programming Language :: Python :: 3
Classifier: Topic :: Software Development
Classifier: Topic :: Utilities
Requires-Dist: astunparse; python_version<'3.9'
Project-URL: changelog, https://github.com/hauntsaninja/pyp/blob/master/CHANGELOG.md
Project-URL: homepage, https://github.com/hauntsaninja/pyp
Project-URL: repository, https://github.com/hauntsaninja/pyp
